financial_calc_br/__init__.py
financial_calc_br/creditCard.py
financial_calc_br/financing.py
financial_calc_br/investments.py
financial_calc_br/rates.py
financial_calc_br/utils.py
financial_calc_br-1.0.3.dist-info/licenses/LICENSE
financial_calc_br-1.0.3.dist-info/METADATA
financial_calc_br-1.0.3.dist-info/WHEEL
financial_calc_br-1.0.3.dist-info/top_level.txt
financial_calc_br-1.0.3.dist-info/RECORD
