Metadata-Version: 2.4
Name: financial_calc_br
Version: 1.0.3
Summary: Calculadora financeira brasileira com suporte a financiamentos, investimentos e cartão de crédito.
Author-email: Lucas Andrade Nascimento <alucad79@gmail.com>, Raul Cabral <raulcabralc@gmail.com>
Project-URL: Homepage, https://github.com/lucansdev/financial-calc-br
Project-URL: Bug Tracker, https://github.com/lucansdev/financial-calc-br/issues
Classifier: Programming Language :: Python :: 3
Classifier: License :: OSI Approved :: MIT License
Classifier: Operating System :: OS Independent
Requires-Python: >=3.7
License-File: LICENSE
Requires-Dist: requests
Dynamic: license-file
